fredlock/__init__.py
fredlock/__main__.py
fredlock/cli.py
fredlock/config.py
fredlock/executor.py
fredlock/fredlock.py
fredlock/main.py
fredlock/utils.py
tests/__init__.py
tests/test_fredlock.py
fredlock-0.1.3.dist-info/LICENSE
fredlock-0.1.3.dist-info/METADATA
fredlock-0.1.3.dist-info/WHEEL
fredlock-0.1.3.dist-info/entry_points.txt
fredlock-0.1.3.dist-info/top_level.txt
fredlock-0.1.3.dist-info/RECORD
