Metadata-Version: 2.1
Name: fredlock
Version: 0.1.3
Summary: Tool to use Redis RedLock algorithm from command line/shell scripts
Home-page: https://mlasevich.github.io/fredlock/
Author: Michael Lasevich
Author-email: mlasevich+fredlock@gmail.com
License: Apache 2.0
Classifier: Programming Language :: Python :: 3 :: Only
Classifier: Programming Language :: Python :: 3.6
Classifier: Programming Language :: Python :: 3.7
Classifier: Programming Language :: Python :: 3.8
Classifier: Programming Language :: Python :: 3.9
Classifier: Programming Language :: Python :: 3.10
Classifier: Programming Language :: Python :: 3.11
Classifier: License :: OSI Approved :: Apache Software License
Classifier: Operating System :: OS Independent
License-File: LICENSE
Requires-Dist: pottery
Requires-Dist: click
Requires-Dist: pyyaml
Requires-Dist: dataclasses ; python_version < "3.7"
Requires-Dist: redis (<4.1.0) ; python_version < "3.7"
